README.md
setup.py
Medium_Search.egg-info/PKG-INFO
Medium_Search.egg-info/SOURCES.txt
Medium_Search.egg-info/dependency_links.txt
Medium_Search.egg-info/top_level.txt
medium/__init__.py
medium/search.py