Metadata-Version: 2.1
Name: Medium-Search
Version: 0.0.5
Summary: Search Medium stories using Python
Home-page: UNKNOWN
Author: Markus Urban
Author-email: murbanlavalira@gmail.com
License: UNKNOWN
Platform: UNKNOWN
Classifier: Development Status :: 3 - Alpha
Classifier: Intended Audience :: Developers
Classifier: Programming Language :: Python :: 3
Classifier: License :: Freeware
Classifier: Natural Language :: English
Classifier: Operating System :: OS Independent
Classifier: Topic :: Internet :: WWW/HTTP :: Indexing/Search
Requires: bs4
Requires: requests
Requires: json
Requires: logging
